rw_96x8_sync.v
module rw_96x8_sync
	(output reg [7:0] data_out,
	 input wire [7:0] address,
	 input wire       WE,
	 input wire [7:0] data_in,
	 input wire       clk);
	 
	 reg[7:0] RW[128:223];
	 wire EN;
	 
	 always @ (address) 
	 	begin
		if ( (address >= 128) && (address <= 223) ) 
			EN = 1’b1;
		else
			EN = 1’b0;
		end
	 
	 always @ (posedge clk)
	 	begin
	 		if (WE && EN)
	 			RW[address] = data_in;
	 		else if (!WE && EN)
	 			data_out = RW[address];
	 	end
	 		
endmodule

projeto_computador/rom_128x8_sync.v
`ifndef ROM_128X8_SYNC_V
`define ROM_128X8_SYNC_V
module rom_128x8_sync
(output reg [7:0] data_out,
	input wire [7:0] address,
	input wire clk);
	
		reg[7:0] ROM[0:127];
		reg EN;
		
		// Mnemonics of Instruction Set
		// Feel free to add other
		
		// Loads and Stores
		parameter LDA_IMM = 8'h86; // Load Register A (Immediate Addressing)
		parameter LDA_DIR = 8'h87; // Load Register A from memory (RAM or IO) (Direct Addressing)
		parameter LDB_IMM = 8'h88; // Load Register B (Immediate Addressing)
		parameter LDB_DIR = 8'h89; // Load Register B from memory (RAM or IO) (Direct Addressing)
		parameter STA_DIR = 8'h96; // Store Register A to memory (RAM or IO)
		parameter STB_DIR = 8'h97; // Store Register B to memory (RAM or IO)
		
		// Data Manipulations
		parameter ADD_AB = 8'h42; // A <= A + B
		parameter SUB_AB = 8'h43; // A <= A - B
		parameter AND_AB = 8'h44; // A <= A & B
		parameter OR_AB = 8'h45; // A <= A | B
		parameter INCA = 8'h46; // A <= A + 1
		parameter INCB = 8'h47; // B <= B + 1
		parameter DECA = 8'h48; // A <= A - 1
		parameter DECB = 8'h49; // B <= B - 1
		parameter XOR_AB = 8'h4A; // A <= A ^ B
		parameter NOTA = 8'h4B; // A <= ~A
		parameter NOTB = 8'h4C; // B <= ~B
		parameter ADDAB_LDB = 8'h4D; // B <= A + B

		// Branches
		parameter BRA = 8'h20; // Branch Always    to (ROM) Address
		parameter BMI = 8'h21; // Branch if N == 1 to (ROM) Address
		parameter BPL = 8'h22; // Branch if N == 0 to (ROM) Address
		parameter BEQ = 8'h23; // Branch if Z == 1 to (ROM) Address
		parameter BNE = 8'h24; // Branch if Z == 0 to (ROM) Address
		parameter BVS = 8'h25; // Branch if V == 1 to (ROM) Address 
		parameter BVC = 8'h26; // Branch if V == 0 to (ROM) Address
		parameter BCS = 8'h27; // Branch if C == 1 to (ROM) Address
		parameter BCC = 8'h28; // Branch if C == 0 to (ROM) Address
		
		
		
		initial 
		begin: PROGRAM_CODE // fibonacci
			ROM[0] = LDA_IMM;  
			ROM[1] = 8'h00;
			ROM[2] = LDB_IMM;
			ROM[3] = 8'h01;
			ROM[4] = ADD_AB;
			ROM[5] = STA_DIR;
			ROM[6] = 8'hE0;
			ROM[7] = ADDAB_LDB;
			ROM[8] = STB_DIR;
			ROM[9] = 8'hE1;
			ROM[10] = BVC;
			ROM[11] = 8'h04;
		end

		
		always @ (address) 
		begin: ADDRESS_LIMITS
			if (address <= 127)
				EN = 1'b1;
			else
				EN = 1'b0;
		end
		
		always @ (posedge clk)
		if (EN)
			data_out = ROM[address];
	 		

endmodule
`endif

projeto_computador/port_out8_sync.v
module port_out8_sync
	(output reg [7:0] port_out_00,
	 output reg [7:0] port_out_01,
	 output reg [7:0] port_out_02,
	 output reg [7:0] port_out_03,
	 output reg [7:0] port_out_04,
	 output reg [7:0] port_out_05,
	 output reg [7:0] port_out_06,
	 output reg [7:0] port_out_07,
	 output reg [7:0] port_out_08,
	 output reg [7:0] port_out_09,
	 output reg [7:0] port_out_10,
	 output reg [7:0] port_out_11,
	 output reg [7:0] port_out_12,
	 output reg [7:0] port_out_13,
	 output reg [7:0] port_out_14,
	 output reg [7:0] port_out_15,
	 input wire [7:0] address,
	 input wire [7:0] data_in,
	 input wire write, clk, reset);
	 
	 // port_out_00 (address E0)
	 always @ (posedge clk or negedge reset)
		begin
			if (!reset)
				port_out_00 <= 8'h00; 
			else if ((address == 8'hE0) && (write))
				port_out_00 <= data_in;
		end
				
	 // port_out_01 (address E2)
	 always @ (posedge clk or negedge reset)
		begin
			if (!reset)
				port_out_01 <= 8'h00; 
			else if ((address == 8'hE1) && (write))
				port_out_01 <= data_in;
		end
		
	 // port_out_02 (address E2)
	 always @ (posedge clk or negedge reset)
		begin
			if (!reset)
				port_out_02 <= 8'h00; 
			else if ((address == 8'hE2) && (write))
				port_out_02 <= data_in;
		end	
		
	 // port_out_03 (address E3)
	 always @ (posedge clk or negedge reset)
		begin
			if (!reset)
				port_out_03 <= 8'h00; 
			else if ((address == 8'hE3) && (write))
				port_out_03 <= data_in;
		end	
		
	 // port_out_04 (address E4)
	 always @ (posedge clk or negedge reset)
		begin
			if (!reset)
				port_out_04 <= 8'h00; 
			else if ((address == 8'hE4) && (write))
				port_out_04 <= data_in;
		end	
	 	
	 // port_out_05 (address E5)		
	 always @ (posedge clk or negedge reset)
		begin
			if (!reset)
				port_out_05 <= 8'h00; 
			else if ((address == 8'hE5) && (write))
				port_out_05 <= data_in;
		end
		
	 // port_out_06 (address E6)		
	 always @ (posedge clk or negedge reset)
		begin
			if (!reset)
				port_out_06 <= 8'h00; 
			else if ((address == 8'hE6) && (write))
				port_out_06 <= data_in;
		end	
		
	 // port_out_07 (address E7)		
	 always @ (posedge clk or negedge reset)
		begin
			if (!reset)
				port_out_07 <= 8'h00; 
			else if ((address == 8'hE7) && (write))
				port_out_07 <= data_in;
		end	
		
	 // port_out_08 (address E8)		
	 always @ (posedge clk or negedge reset)
		begin
			if (!reset)
				port_out_08 <= 8'h00; 
			else if ((address == 8'hE8) && (write))
				port_out_08 <= data_in;
		end	
		
	 // port_out_09 (address E9)		
	 always @ (posedge clk or negedge reset)
		begin
			if (!reset)
				port_out_09 <= 8'h00; 
			else if ((address == 8'hE9) && (write))
				port_out_09 <= data_in;
		end	
		
	 // port_out_10 (address EA)		
	 always @ (posedge clk or negedge reset)
		begin
			if (!reset)
				port_out_10 <= 8'h00; 
			else if ((address == 8'hEA) && (write))
				port_out_10 <= data_in;
		end	
		
	 // port_out_11 (address EB)		
	 always @ (posedge clk or negedge reset)
		begin
			if (!reset)
				port_out_11 <= 8'h00; 
			else if ((address == 8'hEB) && (write))
				port_out_11 <= data_in;
		end	
		
	 // port_out_12 (address EC)		
	 always @ (posedge clk or negedge reset)
		begin
			if (!reset)
				port_out_12 <= 8'h00; 
			else if ((address == 8'hEC) && (write))
				port_out_12 <= data_in;
		end	
		
	 // port_out_13 (address ED)		
	 always @ (posedge clk or negedge reset)
		begin
			if (!reset)
				port_out_13 <= 8'h00; 
			else if ((address == 8'hED) && (write))
				port_out_13 <= data_in;
		end
		
	 // port_out_14 (address EE)		
	 always @ (posedge clk or negedge reset)
		begin
			if (!reset)
				port_out_14 <= 8'h00; 
			else if ((address == 8'hEE) && (write))
				port_out_14 <= data_in;
		end	
		
	 // port_out_15 (address EF)		
	 always @ (posedge clk or negedge reset)
		begin
			if (!reset)
				port_out_15 <= 8'h00; 
			else if ((address == 8'hEF) && (write))
				port_out_15 <= data_in;
		end					
endmodule

projeto_computador/memory.v
`include "port_out8_sync.v"
`include "rom_128x8_sync.v"
`include "rw_96x8_sync.v"

module memory 
	(output wire [7:0] port_out_00,
	 output wire [7:0] port_out_01,
	 output wire [7:0] port_out_02,
	 output wire [7:0] port_out_03,
	 output wire [7:0] port_out_04,
	 output wire [7:0] port_out_05,
	 output wire [7:0] port_out_06,
	 output wire [7:0] port_out_07,
	 output wire [7:0] port_out_08,
	 output wire [7:0] port_out_09,
	 output wire [7:0] port_out_10,
	 output wire [7:0] port_out_11,
	 output wire [7:0] port_out_12,
	 output wire [7:0] port_out_13,
	 output wire [7:0] port_out_14,
	 output wire [7:0] port_out_15,
	 output reg [7:0] data_out,
	 input wire [7:0] address,
	 input wire [7:0] data_in,
	 input wire [7:0] port_in_00,
	 input wire [7:0] port_in_01,
	 input wire [7:0] port_in_02,
	 input wire [7:0] port_in_03,
	 input wire [7:0] port_in_04,
	 input wire [7:0] port_in_05,
	 input wire [7:0] port_in_06,
	 input wire [7:0] port_in_07,
	 input wire [7:0] port_in_08,
	 input wire [7:0] port_in_09,
	 input wire [7:0] port_in_10,
	 input wire [7:0] port_in_11,
	 input wire [7:0] port_in_12,
	 input wire [7:0] port_in_13,
	 input wire [7:0] port_in_14,
	 input wire [7:0] port_in_15,
	 input wire write, clk, reset);
	 
	wire [7:0] rom_data_out, rw_data_out;
	
	always @ (address, rom_data_out, rw_data_out, port_in_00, port_in_01, port_in_02, port_in_03, port_in_04, port_in_05, port_in_06, port_in_07, port_in_08, port_in_09, port_in_10, port_in_11, port_in_12, port_in_13, port_in_14, port_in_15)

		begin: Multiplexing_to_Memory_Data_Bus
			if (address <= 127)
				data_out = rom_data_out;
			else if ( (address >= 128) && (address <= 223) ) 
				data_out = rw_data_out;
			else if (address == 8'hF0) 
				data_out = port_in_00; 
			else if (address == 8'hF1) 
				data_out = port_in_01; 
			else if (address == 8'hF2) 
				data_out = port_in_02; 
			else if (address == 8'hF3) 
				data_out = port_in_03; 
			else if (address == 8'hF4) 
				data_out = port_in_04; 
			else if (address == 8'hF5) 
				data_out = port_in_05; 
			else if (address == 8'hF6) 
				data_out = port_in_06; 
			else if (address == 8'hF7) 
				data_out = port_in_07; 
			else if (address == 8'hF8) 
				data_out = port_in_08; 
			else if (address == 8'hF9) 
				data_out = port_in_09; 
			else if (address == 8'hFA) 
				data_out = port_in_10; 
			else if (address == 8'hFB) 
				data_out = port_in_11; 
			else if (address == 8'hFC) 
				data_out = port_in_12; 
			else if (address == 8'hFD) 
				data_out = port_in_13; 
			else if (address == 8'hFE) 
				data_out = port_in_14; 
			else if (address == 8'hFF) 
				data_out = port_in_15;
		end
	
	port_out8_sync output0 (
		.port_out_00(port_out_00),
		.port_out_01(port_out_01),
		.port_out_02(port_out_02),
		.port_out_03(port_out_03),
		.port_out_04(port_out_04),
		.port_out_05(port_out_05),
		.port_out_06(port_out_06),
		.port_out_07(port_out_07),
		.port_out_08(port_out_08),
		.port_out_09(port_out_09),
		.port_out_10(port_out_10),
		.port_out_11(port_out_11),
		.port_out_12(port_out_12),
		.port_out_13(port_out_13),
		.port_out_14(port_out_14),
		.port_out_15(port_out_15),
		.address(address),
		.data_in(data_in),
		.write(write),
		.clk(clk),
		.reset(reset)
	);
	 		
	rom_128x8_sync read_only_mem(
		.data_out(rom_data_out),
		.address(address),
		.clk(clk)
	);

	rw_96x8_sync read_and_write_mem(
		.data_out(rw_data_out),
		.address(address),
		.data_in(data_in),
		.WE(write),
		.clk(clk)
	);


endmodule

projeto_computador/memory_TB.v
`timescale 100ns/1ps
`include "memory.v"

module memory_TB;
    reg clk = 0;
    reg reset = 0;
    reg write = 0;
    reg [7:0] address = 8'h00;
    reg [7:0] data_in = 8'h00;

    // Entradas das portas
    reg [7:0] port_in_00 = 8'hAA;
    reg [7:0] port_in_01 = 8'hBB;
    reg [7:0] port_in_15 = 8'hFF;

    // Saídas das portas
    wire [7:0] port_out_00;
    wire [7:0] port_out_01;
    wire [7:0] port_out_02;
    wire [7:0] port_out_03;
    wire [7:0] port_out_04;
    wire [7:0] port_out_05;
    wire [7:0] port_out_06;
    wire [7:0] port_out_07;
    wire [7:0] port_out_08;
    wire [7:0] port_out_09;
    wire [7:0] port_out_10;
    wire [7:0] port_out_11;
    wire [7:0] port_out_12;
    wire [7:0] port_out_13;
    wire [7:0] port_out_14;
    wire [7:0] port_out_15;

    wire [7:0] data_out;

    memory DUT (
        .port_out_00(port_out_00), .port_out_01(port_out_01),
        .port_out_02(port_out_02), .port_out_03(port_out_03),
        .port_out_04(port_out_04), .port_out_05(port_out_05),
        .port_out_06(port_out_06), .port_out_07(port_out_07),
        .port_out_08(port_out_08), .port_out_09(port_out_09),
        .port_out_10(port_out_10), .port_out_11(port_out_11),
        .port_out_12(port_out_12), .port_out_13(port_out_13),
        .port_out_14(port_out_14), .port_out_15(port_out_15),
        .data_out(data_out),
        .address(address),
        .data_in(data_in),
        .port_in_00(port_in_00), .port_in_01(port_in_01),
        .port_in_02(8'h00), .port_in_03(8'h00),
        .port_in_04(8'h00), .port_in_05(8'h00),
        .port_in_06(8'h00), .port_in_07(8'h00),
        .port_in_08(8'h00), .port_in_09(8'h00),
        .port_in_10(8'h00), .port_in_11(8'h00),
        .port_in_12(8'h00), .port_in_13(8'h00),
        .port_in_14(8'h00), .port_in_15(port_in_15),
        .write(write), .clk(clk), .reset(reset)
    );

    always #10 clk = ~clk;

    initial begin
        $dumpfile("memory_TB.vcd");
        $dumpvars(0, memory_TB);

        // Inicialização
        #5 reset = 1;

        // Teste (i): Escrevendo na RAM
        #20 address = 8'h82; data_in = 8'h55; write = 1;
        #20 write = 0;

        // Lendo da RAM
        #40 address = 8'h82;

        // Teste (ii): Lendo da ROM (ex: endereço 0x0A deve conter valor da rom simulada)
        #40 address = 8'h05;

        // Teste (ii): Lendo das portas de entrada (endereços F0, F1, FF)
        #40 address = 8'hF0;
        #40 address = 8'hF1;
        #40 address = 8'hFF;

        // Teste (iii): Escrevendo nas portas de saída (endereços E0, E1, EF)
        #40 address = 8'hE0; data_in = 8'h33; write = 1;
        #20 write = 0;

        #40 address = 8'hE1; data_in = 8'h44; write = 1;
        #20 write = 0;

        #40 address = 8'hEF; data_in = 8'h77; write = 1;
        #20 write = 0;

        #50 $finish;
    end
endmodule

projeto_computador/memory_TB.vcd
$date
	Fri Apr 04 14:03:50 2025
$end
$version
	Icarus Verilog
$end
$timescale
	1ps
$end
$scope module memory_TB $end
$var wire 8 ! port_out_15 [7:0] $end
$var wire 8 " port_out_14 [7:0] $end
$var wire 8 # port_out_13 [7:0] $end
$var wire 8 $ port_out_12 [7:0] $end
$var wire 8 % port_out_11 [7:0] $end
$var wire 8 & port_out_10 [7:0] $end
$var wire 8 ' port_out_09 [7:0] $end
$var wire 8 ( port_out_08 [7:0] $end
$var wire 8 ) port_out_07 [7:0] $end
$var wire 8 * port_out_06 [7:0] $end
$var wire 8 + port_out_05 [7:0] $end
$var wire 8 , port_out_04 [7:0] $end
$var wire 8 - port_out_03 [7:0] $end
$var wire 8 . port_out_02 [7:0] $end
$var wire 8 / port_out_01 [7:0] $end
$var wire 8 0 port_out_00 [7:0] $end
$var wire 8 1 data_out [7:0] $end
$var reg 8 2 address [7:0] $end
$var reg 1 3 clk $end
$var reg 8 4 data_in [7:0] $end
$var reg 8 5 port_in_00 [7:0] $end
$var reg 8 6 port_in_01 [7:0] $end
$var reg 8 7 port_in_15 [7:0] $end
$var reg 1 8 reset $end
$var reg 1 9 write $end
$scope module DUT $end
$var wire 8 : address [7:0] $end
$var wire 1 3 clk $end
$var wire 8 ; data_in [7:0] $end
$var wire 8 < port_in_00 [7:0] $end
$var wire 8 = port_in_01 [7:0] $end
$var wire 8 > port_in_02 [7:0] $end
$var wire 8 ? port_in_03 [7:0] $end
$var wire 8 @ port_in_04 [7:0] $end
$var wire 8 A port_in_05 [7:0] $end
$var wire 8 B port_in_06 [7:0] $end
$var wire 8 C port_in_07 [7:0] $end
$var wire 8 D port_in_08 [7:0] $end
$var wire 8 E port_in_09 [7:0] $end
$var wire 8 F port_in_10 [7:0] $end
$var wire 8 G port_in_11 [7:0] $end
$var wire 8 H port_in_12 [7:0] $end
$var wire 8 I port_in_13 [7:0] $end
$var wire 8 J port_in_14 [7:0] $end
$var wire 8 K port_in_15 [7:0] $end
$var wire 1 8 reset $end
$var wire 1 9 write $end
$var wire 8 L rw_data_out [7:0] $end
$var wire 8 M rom_data_out [7:0] $end
$var wire 8 N port_out_15 [7:0] $end
$var wire 8 O port_out_14 [7:0] $end
$var wire 8 P port_out_13 [7:0] $end
$var wire 8 Q port_out_12 [7:0] $end
$var wire 8 R port_out_11 [7:0] $end
$var wire 8 S port_out_10 [7:0] $end
$var wire 8 T port_out_09 [7:0] $end
$var wire 8 U port_out_08 [7:0] $end
$var wire 8 V port_out_07 [7:0] $end
$var wire 8 W port_out_06 [7:0] $end
$var wire 8 X port_out_05 [7:0] $end
$var wire 8 Y port_out_04 [7:0] $end
$var wire 8 Z port_out_03 [7:0] $end
$var wire 8 [ port_out_02 [7:0] $end
$var wire 8 \ port_out_01 [7:0] $end
$var wire 8 ] port_out_00 [7:0] $end
$var reg 8 ^ data_out [7:0] $end
$scope module output0 $end
$var wire 8 _ address [7:0] $end
$var wire 1 3 clk $end
$var wire 8 ` data_in [7:0] $end
$var wire 1 8 reset $end
$var wire 1 9 write $end
$var reg 8 a port_out_00 [7:0] $end
$var reg 8 b port_out_01 [7:0] $end
$var reg 8 c port_out_02 [7:0] $end
$var reg 8 d port_out_03 [7:0] $end
$var reg 8 e port_out_04 [7:0] $end
$var reg 8 f port_out_05 [7:0] $end
$var reg 8 g port_out_06 [7:0] $end
$var reg 8 h port_out_07 [7:0] $end
$var reg 8 i port_out_08 [7:0] $end
$var reg 8 j port_out_09 [7:0] $end
$var reg 8 k port_out_10 [7:0] $end
$var reg 8 l port_out_11 [7:0] $end
$var reg 8 m port_out_12 [7:0] $end
$var reg 8 n port_out_13 [7:0] $end
$var reg 8 o port_out_14 [7:0] $end
$var reg 8 p port_out_15 [7:0] $end
$upscope $end
$scope module read_and_write_mem $end
$var wire 1 9 WE $end
$var wire 8 q address [7:0] $end
$var wire 1 3 clk $end
$var wire 8 r data_in [7:0] $end
$var reg 1 s EN $end
$var reg 8 t data_out [7:0] $end
$upscope $end
$scope module read_only_mem $end
$var wire 8 u address [7:0] $end
$var wire 1 3 clk $end
$var parameter 8 v ADDAB_LDB $end
$var parameter 8 w ADD_AB $end
$var parameter 8 x AND_AB $end
$var parameter 8 y BCC $end
$var parameter 8 z BCS $end
$var parameter 8 { BEQ $end
$var parameter 8 | BMI $end
$var parameter 8 } BNE $end
$var parameter 8 ~ BPL $end
$var parameter 8 !" BRA $end
$var parameter 8 "" BVC $end
$var parameter 8 #" BVS $end
$var parameter 8 $" DECA $end
$var parameter 8 %" DECB $end
$var parameter 8 &" INCA $end
$var parameter 8 '" INCB $end
$var parameter 8 (" LDA_DIR $end
$var parameter 8 )" LDA_IMM $end
$var parameter 8 *" LDB_DIR $end
$var parameter 8 +" LDB_IMM $end
$var parameter 8 ," NOTA $end
$var parameter 8 -" NOTB $end
$var parameter 8 ." OR_AB $end
$var parameter 8 /" STA_DIR $end
$var parameter 8 0" STB_DIR $end
$var parameter 8 1" SUB_AB $end
$var parameter 8 2" XOR_AB $end
$var reg 1 3" EN $end
$var reg 8 4" data_out [7:0] $end
$scope begin ADDRESS_LIMITS $end
$upscope $end
$scope begin PROGRAM_CODE $end
$upscope $end
$upscope $end
$scope begin Multiplexing_to_Memory_Data_Bus $end
$upscope $end
$upscope $end
$upscope $end
$enddefinitions $end
$comment Show the parameter values. $end
$dumpall
b1001010 2"
b1000011 1"
b10010111 0"
b10010110 /"
b1000101 ."
b1001100 -"
b1001011 ,"
b10001000 +"
b10001001 *"
b10000110 )"
b10000111 ("
b1000111 '"
b1000110 &"
b1001001 %"
b1001000 $"
b100101 #"
b100110 ""
b100000 !"
b100010 ~
b100100 }
b100001 |
b100011 {
b100111 z
b101000 y
b1000100 x
b1000010 w
b1001101 v
$end
#0
$dumpvars
bx 4"
13"
b0 u
bx t
0s
b0 r
b0 q
b0 p
b0 o
b0 n
b0 m
b0 l
b0 k
b0 j
b0 i
b0 h
b0 g
b0 f
b0 e
b0 d
b0 c
b0 b
b0 a
b0 `
b0 _
bx ^
b0 ]
b0 \
b0 [
b0 Z
b0 Y
b0 X
b0 W
b0 V
b0 U
b0 T
b0 S
b0 R
b0 Q
b0 P
b0 O
b0 N
bx M
bx L
b11111111 K
b0 J
b0 I
b0 H
b0 G
b0 F
b0 E
b0 D
b0 C
b0 B
b0 A
b0 @
b0 ?
b0 >
b10111011 =
b10101010 <
b0 ;
b0 :
09
08
b11111111 7
b10111011 6
b10101010 5
b0 4
03
b0 2
bx 1
b0 0
b0 /
b0 .
b0 -
b0 ,
b0 +
b0 *
b0 )
b0 (
b0 '
b0 &
b0 %
b0 $
b0 #
b0 "
b0 !
$end
#500000
18
#1000000
b10000110 1
b10000110 ^
b10000110 M
b10000110 4"
13
#2000000
03
#2500000
03"
1s
bx 1
bx ^
19
b1010101 4
b1010101 ;
b1010101 `
b1010101 r
b10000010 2
b10000010 :
b10000010 _
b10000010 q
b10000010 u
#3000000
13
#4000000
03
#4500000
09
#5000000
b1010101 1
b1010101 ^
b1010101 L
b1010101 t
13
#6000000
03
#7000000
13
#8000000
03
#9000000
13
#10000000
03
#11000000
13
#12000000
03
#12500000
13"
0s
b10000110 1
b10000110 ^
b101 2
b101 :
b101 _
b101 q
b101 u
#13000000
b1001101 1
b1001101 ^
b1001101 M
b1001101 4"
13
#14000000
03
#15000000
13
#16000000
03
#16500000
03"
b10101010 1
b10101010 ^
b11110000 2
b11110000 :
b11110000 _
b11110000 q
b11110000 u
#17000000
13
#18000000
03
#19000000
13
#20000000
03
#20500000
b10111011 1
b10111011 ^
b11110001 2
b11110001 :
b11110001 _
b11110001 q
b11110001 u
#21000000
13
#22000000
03
#23000000
13
#24000000
03
#24500000
b11111111 1
b11111111 ^
b11111111 2
b11111111 :
b11111111 _
b11111111 q
b11111111 u
#25000000
13
#26000000
03
#27000000
13
#28000000
03
#28500000
19
b110011 4
b110011 ;
b110011 `
b110011 r
b11100000 2
b11100000 :
b11100000 _
b11100000 q
b11100000 u
#29000000
b110011 0
b110011 ]
b110011 a
13
#30000000
03
#30500000
09
#31000000
13
#32000000
03
#33000000
13
#34000000
03
#34500000
19
b1000100 4
b1000100 ;
b1000100 `
b1000100 r
b11100001 2
b11100001 :
b11100001 _
b11100001 q
b11100001 u
#35000000
b1000100 /
b1000100 \
b1000100 b
13
#36000000
03
#36500000
09
#37000000
13
#38000000
03
#39000000
13
#40000000
03
#40500000
19
b1110111 4
b1110111 ;
b1110111 `
b1110111 r
b11101111 2
b11101111 :
b11101111 _
b11101111 q
b11101111 u
#41000000
b1110111 !
b1110111 N
b1110111 p
13
#42000000
03
#42500000
09
